sphinxcontrib/autoyaml/__init__.py
sphinxcontrib_autoyaml-1.1.3.dist-info/LICENSE
sphinxcontrib_autoyaml-1.1.3.dist-info/METADATA
sphinxcontrib_autoyaml-1.1.3.dist-info/WHEEL
sphinxcontrib_autoyaml-1.1.3.dist-info/top_level.txt
sphinxcontrib_autoyaml-1.1.3.dist-info/RECORD
