Metadata-Version: 2.1
Name: sphinxcontrib-autoyaml
Version: 1.1.3
Summary: Sphinx autodoc extension for documenting YAML files from comments
Author-email: Jakub Pieńkowski <jakub+sphinxcontrib-autoyaml@jakski.name>
License: MIT
Classifier: Development Status :: 3 - Alpha
Classifier: Framework :: Sphinx :: Extension
Classifier: Intended Audience :: System Administrators
Classifier: License :: OSI Approved :: MIT License
Classifier: Topic :: Documentation
Requires-Python: >=3.6
License-File: LICENSE
Requires-Dist: Sphinx>=3.5.1
Requires-Dist: ruamel.yaml>=0.16.12
Provides-Extra: test
Requires-Dist: sphinx-testing>=1.0.1; extra == "test"
Requires-Dist: flake8>=3.8.4; extra == "test"
